setup.py
csvmysql/__init__.py
csvmysql/load_csv_msql.py
csvmysql.egg-info/PKG-INFO
csvmysql.egg-info/SOURCES.txt
csvmysql.egg-info/dependency_links.txt
csvmysql.egg-info/not-zip-safe
csvmysql.egg-info/requires.txt
csvmysql.egg-info/top_level.txt