Metadata-Version: 1.0
Name: csvmysql
Version: 0.11
Summary: transmit data from csv file to mysql database, date type is not handled in this version
Home-page: https://github.com/ghao2/csvmysql
Author: Guoxuan Hao
Author-email: haoguoxuan@gmail.com
License: MIT
Platform: UNKNOWN
